identitykeys.py
python_identitykeys-0.2.1.dist-info/LICENSE
python_identitykeys-0.2.1.dist-info/METADATA
python_identitykeys-0.2.1.dist-info/WHEEL
python_identitykeys-0.2.1.dist-info/top_level.txt
python_identitykeys-0.2.1.dist-info/RECORD
